COPYING
COPYING-Wireshark
LICENSE
LICENSE-libpcap
README.rst
setup.py
wishpy/__init__.py
wishpy.egg-info/PKG-INFO
wishpy.egg-info/SOURCES.txt
wishpy.egg-info/dependency_links.txt
wishpy.egg-info/entry_points.txt
wishpy.egg-info/not-zip-safe
wishpy.egg-info/requires.txt
wishpy.egg-info/top_level.txt
wishpy/libpcap/__init__.py
wishpy/libpcap/lib/__init__.py
wishpy/libpcap/lib/capturer.py
wishpy/libpcap/lib/pcapy.py
wishpy/libpcap/src/__init__.py
wishpy/libpcap/src/bpf_h.py
wishpy/libpcap/src/dlt_h.py
wishpy/libpcap/src/pcap.py
wishpy/libpcap/src/pcap_builder.py
wishpy/libpcap/src/pcap_h.py
wishpy/libpcap/src/pcap_h_18.py
wishpy/libpcap/src/typedefs_h.py
wishpy/scripts/__init__.py
wishpy/scripts/pcap_to_pickle.py
wishpy/scripts/tcpdump.py
wishpy/scripts/tshark.py
wishpy/utils/__init__.py
wishpy/utils/profiler.py
wishpy/wireshark/__init__.py
wishpy/wireshark/lib/__init__.py
wishpy/wireshark/lib/_wrapper.py
wishpy/wireshark/lib/dissector.py
wishpy/wireshark/lib/fake_ext.py
wishpy/wireshark/src/__init__.py
wishpy/wireshark/src/wishpy_types_h.py
wishpy/wireshark/src/ws_symbols_h.py
wishpy/wireshark/src/glib/__init__.py
wishpy/wireshark/src/glib/garray_h.py
wishpy/wireshark/src/glib/ghash_h.py
wishpy/wireshark/src/glib/glib_h.py
wishpy/wireshark/src/glib/glib_win_h.py
wishpy/wireshark/src/glib/glist_h.py
wishpy/wireshark/src/glib/gstring_h.py
wishpy/wireshark/src/wireshark2/__init__.py
wishpy/wireshark/src/wireshark2/epan/__init__.py
wishpy/wireshark/src/wireshark2/epan/address_h.py
wishpy/wireshark/src/wireshark2/epan/dfilter_h.py
wishpy/wireshark/src/wireshark2/epan/epan.py
wishpy/wireshark/src/wireshark2/epan/epan_builder.py
wishpy/wireshark/src/wireshark2/epan/epan_dissect_h.py
wishpy/wireshark/src/wireshark2/epan/epan_h.py
wishpy/wireshark/src/wireshark2/epan/framedata_h.py
wishpy/wireshark/src/wireshark2/epan/ftypes_h.py
wishpy/wireshark/src/wireshark2/epan/guid_utils_h.py
wishpy/wireshark/src/wireshark2/epan/packet_h.py
wishpy/wireshark/src/wireshark2/epan/packet_info_h.py
wishpy/wireshark/src/wireshark2/epan/params_h.py
wishpy/wireshark/src/wireshark2/epan/prefs_h.py
wishpy/wireshark/src/wireshark2/epan/print_h.py
wishpy/wireshark/src/wireshark2/epan/print_stream_h.py
