Metadata-Version: 1.1
Name: wishpy
Version: 0.1.1
Summary: Python Bindings for Wireshark and libpcap using cffi
Home-page: https://github.com/hyphenOs/wishpy/
Author: hyphenOs Software Labs
Author-email: gabhijit@hyphenos.io
License: GPLv3
Keywords: Python,Wireshark,Networking,libpcap
Platform: UNKNOWN
Classifier: Development Status :: 2 - Pre-Alpha
Classifier: Environment :: Console
Classifier: Intended Audience :: Developers
Classifier: Intended Audience :: System Administrators
Classifier: Intended Audience :: Telecommunications Industry
Classifier: License :: OSI Approved :: GNU General Public License v2 (GPLv2)
Classifier: Programming Language :: Python :: 3
Classifier: Programming Language :: Python :: 3.5
Classifier: Programming Language :: Python :: 3.6
Classifier: Programming Language :: Python :: 3.7
Classifier: Programming Language :: Python :: 3.8
Classifier: Topic :: System :: Networking
Classifier: Topic :: System :: Networking :: Monitoring
